covidwrapper/__init__.py
covidwrapper/covid.py
tests/__init__.py
tests/test_all_data.py
tests/test_cases_by_countries.py
tests/test_countries.py
tests/test_live_cases_by_country.py
tests/test_summary.py
tests/test_total_cases_by_countries.py
pyvid19-0.0.1.dist-info/METADATA
pyvid19-0.0.1.dist-info/WHEEL
pyvid19-0.0.1.dist-info/top_level.txt
pyvid19-0.0.1.dist-info/RECORD
